setup.py
json_cpp/__init__.py
json_cpp/decorators.py
json_cpp/json_object.py
json_cpp/search.py
json_cpp/util.py
json_cpp.egg-info/PKG-INFO
json_cpp.egg-info/SOURCES.txt
json_cpp.egg-info/dependency_links.txt
json_cpp.egg-info/not-zip-safe
json_cpp.egg-info/requires.txt
json_cpp.egg-info/top_level.txt