Metadata-Version: 2.1
Name: json-cpp
Version: 1.0.108
Summary: a better json library
Home-page: UNKNOWN
Author: german espinosa
Author-email: germanespinosa@gmail.com
License: MIT
Platform: UNKNOWN
